[
   {
      "no":1,
      "image_id":75,
      "image_upload":"Apps/master/db-1/imgs/pic0.jpg",
      "image_url":"",
      "type":"upload",
      "view_count":"624",
      "download_count":"197",
      "featured":"yes",
      "tags":"aesthetic wallpaper",
      "category_id":"16",
      "category_name":"aesthetic wallpaper"
   },
   {
      "no":2,
      "image_id":74,
      "image_upload":"Apps/master/db-1/imgs/pic1.jpg",
      "image_url":"",
      "type":"upload",
      "view_count":"624",
      "download_count":"197",
      "featured":"yes",
      "tags":"aesthetic wallpaper",
      "category_id":"16",
      "category_name":"aesthetic wallpaper"
   },
   {
      "no":3,
      "image_id":73,
      "image_upload":"Apps/master/db-1/imgs/pic2.jpg",
      "image_url":"",
      "type":"upload",
      "view_count":"624",
      "download_count":"197",
      "featured":"yes",
      "tags":"aesthetic wallpaper",
      "category_id":"16",
      "category_name":"aesthetic wallpaper"
   },
   {
      "no":4,
      "image_id":72,
      "image_upload":"Apps/master/db-1/imgs/pic3.jpg",
      "image_url":"",
      "type":"upload",
      "view_count":"624",
      "download_count":"197",
      "featured":"yes",
      "tags":"aesthetic wallpaper",
      "category_id":"16",
      "category_name":"aesthetic wallpaper"
   },
   {
      "no":5,
      "image_id":71,
      "image_upload":"Apps/master/db-1/imgs/pic4.jpg",
      "image_url":"",
      "type":"upload",
      "view_count":"624",
      "download_count":"197",
      "featured":"yes",
      "tags":"aesthetic wallpaper",
      "category_id":"16",
      "category_name":"aesthetic wallpaper"
   },
   {
      "no":6,
      "image_id":70,
      "image_upload":"Apps/master/db-1/imgs/pic5.jpg",
      "image_url":"",
      "type":"upload",
      "view_count":"624",
      "download_count":"197",
      "featured":"yes",
      "tags":"aesthetic wallpaper",
      "category_id":"16",
      "category_name":"aesthetic wallpaper"
   },
   {
      "no":7,
      "image_id":69,
      "image_upload":"Apps/master/db-1/imgs/pic6.jpg",
      "image_url":"",
      "type":"upload",
      "view_count":"624",
      "download_count":"197",
      "featured":"yes",
      "tags":"aesthetic wallpaper",
      "category_id":"16",
      "category_name":"aesthetic wallpaper"
   },
   {
      "no":8,
      "image_id":68,
      "image_upload":"Apps/master/db-1/imgs/pic7.jpg",
      "image_url":"",
      "type":"upload",
      "view_count":"624",
      "download_count":"197",
      "featured":"yes",
      "tags":"aesthetic wallpaper",
      "category_id":"16",
      "category_name":"aesthetic wallpaper"
   },
   {
      "no":9,
      "image_id":67,
      "image_upload":"Apps/master/db-1/imgs/pic8.jpg",
      "image_url":"",
      "type":"upload",
      "view_count":"624",
      "download_count":"197",
      "featured":"yes",
      "tags":"aesthetic wallpaper",
      "category_id":"16",
      "category_name":"aesthetic wallpaper"
   },
   {
      "no":10,
      "image_id":66,
      "image_upload":"Apps/master/db-1/imgs/pic9.jpg",
      "image_url":"",
      "type":"upload",
      "view_count":"624",
      "download_count":"197",
      "featured":"yes",
      "tags":"aesthetic wallpaper",
      "category_id":"16",
      "category_name":"aesthetic wallpaper"
   },
   {
      "no":11,
      "image_id":65,
      "image_upload":"Apps/master/db-1/imgs/pic10.jpg",
      "image_url":"",
      "type":"upload",
      "view_count":"624",
      "download_count":"197",
      "featured":"yes",
      "tags":"aesthetic wallpaper",
      "category_id":"16",
      "category_name":"aesthetic wallpaper"
   },
   {
      "no":12,
      "image_id":64,
      "image_upload":"Apps/master/db-1/imgs/pic11.jpg",
      "image_url":"",
      "type":"upload",
      "view_count":"624",
      "download_count":"197",
      "featured":"yes",
      "tags":"aesthetic wallpaper",
      "category_id":"16",
      "category_name":"aesthetic wallpaper"
   },
   {
      "no":13,
      "image_id":63,
      "image_upload":"Apps/master/db-1/imgs/pic12.jpg",
      "image_url":"",
      "type":"upload",
      "view_count":"624",
      "download_count":"197",
      "featured":"yes",
      "tags":"aesthetic wallpaper",
      "category_id":"16",
      "category_name":"aesthetic wallpaper"
   },
   {
      "no":14,
      "image_id":62,
      "image_upload":"Apps/master/db-1/imgs/pic13.jpg",
      "image_url":"",
      "type":"upload",
      "view_count":"624",
      "download_count":"197",
      "featured":"yes",
      "tags":"aesthetic wallpaper",
      "category_id":"16",
      "category_name":"aesthetic wallpaper"
   },
   {
      "no":15,
      "image_id":61,
      "image_upload":"Apps/master/db-1/imgs/pic14.jpg",
      "image_url":"",
      "type":"upload",
      "view_count":"624",
      "download_count":"197",
      "featured":"yes",
      "tags":"aesthetic wallpaper",
      "category_id":"16",
      "category_name":"aesthetic wallpaper"
   },
   {
      "no":16,
      "image_id":60,
      "image_upload":"Apps/master/db-1/imgs/pic15.jpg",
      "image_url":"",
      "type":"upload",
      "view_count":"624",
      "download_count":"197",
      "featured":"yes",
      "tags":"aesthetic wallpaper",
      "category_id":"16",
      "category_name":"aesthetic wallpaper"
   },
   {
      "no":17,
      "image_id":59,
      "image_upload":"Apps/master/db-1/imgs/pic16.jpg",
      "image_url":"",
      "type":"upload",
      "view_count":"624",
      "download_count":"197",
      "featured":"yes",
      "tags":"aesthetic wallpaper",
      "category_id":"16",
      "category_name":"aesthetic wallpaper"
   },
   {
      "no":18,
      "image_id":58,
      "image_upload":"Apps/master/db-1/imgs/pic17.jpg",
      "image_url":"",
      "type":"upload",
      "view_count":"624",
      "download_count":"197",
      "featured":"yes",
      "tags":"aesthetic wallpaper",
      "category_id":"16",
      "category_name":"aesthetic wallpaper"
   },
   {
      "no":19,
      "image_id":57,
      "image_upload":"Apps/master/db-1/imgs/pic18.jpg",
      "image_url":"",
      "type":"upload",
      "view_count":"624",
      "download_count":"197",
      "featured":"yes",
      "tags":"aesthetic wallpaper",
      "category_id":"16",
      "category_name":"aesthetic wallpaper"
   },
   {
      "no":20,
      "image_id":56,
      "image_upload":"Apps/master/db-1/imgs/pic19.jpg",
      "image_url":"",
      "type":"upload",
      "view_count":"624",
      "download_count":"197",
      "featured":"yes",
      "tags":"aesthetic wallpaper",
      "category_id":"16",
      "category_name":"aesthetic wallpaper"
   },
   {
      "no":21,
      "image_id":55,
      "image_upload":"Apps/master/db-1/imgs/pic20.jpg",
      "image_url":"",
      "type":"upload",
      "view_count":"624",
      "download_count":"197",
      "featured":"yes",
      "tags":"aesthetic wallpaper",
      "category_id":"16",
      "category_name":"aesthetic wallpaper"
   },
   {
      "no":22,
      "image_id":54,
      "image_upload":"Apps/master/db-1/imgs/pic21.jpg",
      "image_url":"",
      "type":"upload",
      "view_count":"624",
      "download_count":"197",
      "featured":"yes",
      "tags":"aesthetic wallpaper",
      "category_id":"16",
      "category_name":"aesthetic wallpaper"
   },
   {
      "no":23,
      "image_id":53,
      "image_upload":"Apps/master/db-1/imgs/pic22.jpg",
      "image_url":"",
      "type":"upload",
      "view_count":"624",
      "download_count":"197",
      "featured":"yes",
      "tags":"aesthetic wallpaper",
      "category_id":"16",
      "category_name":"aesthetic wallpaper"
   },
   {
      "no":24,
      "image_id":52,
      "image_upload":"Apps/master/db-1/imgs/pic23.jpg",
      "image_url":"",
      "type":"upload",
      "view_count":"624",
      "download_count":"197",
      "featured":"yes",
      "tags":"aesthetic wallpaper",
      "category_id":"16",
      "category_name":"aesthetic wallpaper"
   },
   {
      "no":25,
      "image_id":51,
      "image_upload":"Apps/master/db-1/imgs/pic24.jpg",
      "image_url":"",
      "type":"upload",
      "view_count":"624",
      "download_count":"197",
      "featured":"yes",
      "tags":"aesthetic wallpaper",
      "category_id":"16",
      "category_name":"aesthetic wallpaper"
   },
   {
      "no":26,
      "image_id":50,
      "image_upload":"Apps/master/db-1/imgs/pic25.jpg",
      "image_url":"",
      "type":"upload",
      "view_count":"624",
      "download_count":"197",
      "featured":"yes",
      "tags":"aesthetic wallpaper",
      "category_id":"16",
      "category_name":"aesthetic wallpaper"
   },
   {
      "no":27,
      "image_id":49,
      "image_upload":"Apps/master/db-1/imgs/pic26.jpg",
      "image_url":"",
      "type":"upload",
      "view_count":"624",
      "download_count":"197",
      "featured":"yes",
      "tags":"aesthetic wallpaper",
      "category_id":"16",
      "category_name":"aesthetic wallpaper"
   },
   {
      "no":28,
      "image_id":48,
      "image_upload":"Apps/master/db-1/imgs/pic27.jpg",
      "image_url":"",
      "type":"upload",
      "view_count":"624",
      "download_count":"197",
      "featured":"yes",
      "tags":"aesthetic wallpaper",
      "category_id":"16",
      "category_name":"aesthetic wallpaper"
   },
   {
      "no":29,
      "image_id":47,
      "image_upload":"Apps/master/db-1/imgs/pic28.jpg",
      "image_url":"",
      "type":"upload",
      "view_count":"624",
      "download_count":"197",
      "featured":"yes",
      "tags":"aesthetic wallpaper",
      "category_id":"16",
      "category_name":"aesthetic wallpaper"
   },
   {
      "no":30,
      "image_id":46,
      "image_upload":"Apps/master/db-1/imgs/pic29.jpg",
      "image_url":"",
      "type":"upload",
      "view_count":"624",
      "download_count":"197",
      "featured":"yes",
      "tags":"aesthetic wallpaper",
      "category_id":"16",
      "category_name":"aesthetic wallpaper"
   }
]
